mistraldashboard/__init__.py
mistraldashboard/api.py
mistraldashboard/dashboard.py
mistraldashboard/exceptions.py
mistraldashboard/forms.py
mistraldashboard/handle_errors.py
mistraldashboard/action_executions/__init__.py
mistraldashboard/action_executions/forms.py
mistraldashboard/action_executions/panel.py
mistraldashboard/action_executions/tables.py
mistraldashboard/action_executions/tests.py
mistraldashboard/action_executions/urls.py
mistraldashboard/action_executions/views.py
mistraldashboard/action_executions/templates/action_executions/_update.html
mistraldashboard/action_executions/templates/action_executions/detail.html
mistraldashboard/action_executions/templates/action_executions/filtered.html
mistraldashboard/action_executions/templates/action_executions/index.html
mistraldashboard/action_executions/templates/action_executions/update.html
mistraldashboard/actions/__init__.py
mistraldashboard/actions/forms.py
mistraldashboard/actions/panel.py
mistraldashboard/actions/tables.py
mistraldashboard/actions/tests.py
mistraldashboard/actions/urls.py
mistraldashboard/actions/views.py
mistraldashboard/actions/templates/actions/_create.html
mistraldashboard/actions/templates/actions/_run.html
mistraldashboard/actions/templates/actions/_update.html
mistraldashboard/actions/templates/actions/create.html
mistraldashboard/actions/templates/actions/detail.html
mistraldashboard/actions/templates/actions/index.html
mistraldashboard/actions/templates/actions/run.html
mistraldashboard/actions/templates/actions/update.html
mistraldashboard/cron_triggers/__init__.py
mistraldashboard/cron_triggers/forms.py
mistraldashboard/cron_triggers/panel.py
mistraldashboard/cron_triggers/tables.py
mistraldashboard/cron_triggers/tests.py
mistraldashboard/cron_triggers/urls.py
mistraldashboard/cron_triggers/views.py
mistraldashboard/cron_triggers/templates/cron_triggers/_create.html
mistraldashboard/cron_triggers/templates/cron_triggers/create.html
mistral_dashboard-21.0.0.dist-info/AUTHORS
mistral_dashboard-21.0.0.dist-info/LICENSE
mistral_dashboard-21.0.0.dist-info/METADATA
mistral_dashboard-21.0.0.dist-info/WHEEL
mistral_dashboard-21.0.0.dist-info/pbr.json
mistral_dashboard-21.0.0.dist-info/top_level.txt
mistral_dashboard-21.0.0.dist-info/RECORD
