Metadata-Version: 2.1
Name: mistral-dashboard
Version: 21.0.0
Summary: Mistral dashboard
Home-page: https://docs.openstack.org/mistral/latest/
Author: OpenStack
Author-email: openstack-discuss@lists.openstack.org
License: Apache-2.0
Classifier: Environment :: OpenStack
Classifier: Intended Audience :: Information Technology
Classifier: Intended Audience :: System Administrators
Classifier: Operating System :: POSIX :: Linux
Classifier: Programming Language :: Python
Classifier: Programming Language :: Python :: Implementation :: CPython
Classifier: Programming Language :: Python :: 3 :: Only
Classifier: Programming Language :: Python :: 3
Classifier: Programming Language :: Python :: 3.10
Classifier: Programming Language :: Python :: 3.11
Classifier: Programming Language :: Python :: 3.12
Classifier: Programming Language :: Python :: 3.13
Requires-Python: >=3.10
License-File: LICENSE
License-File: AUTHORS
Requires-Dist: pbr !=2.1.0,>=2.0.0
Requires-Dist: python-mistralclient >=4.3.0
Requires-Dist: PyYAML >=3.12
Requires-Dist: horizon >=23.1.1
